dewy_langchain/__init__.py
dewy_langchain/retriever.py
dewy_langchain-0.3.0.dist-info/METADATA
dewy_langchain-0.3.0.dist-info/WHEEL
dewy_langchain-0.3.0.dist-info/RECORD
