Metadata-Version: 2.1
Name: dewy-langchain
Version: 0.3.0
Summary: 
Author: Ben Chambers
Author-email: 35960+bjchambers@users.noreply.github.com
Requires-Python: >=3.11,<4.0
Classifier: Programming Language :: Python :: 3
Classifier: Programming Language :: Python :: 3.11
Classifier: Programming Language :: Python :: 3.12
Requires-Dist: dewy-client (>=0.3.0,<0.4.0)
Requires-Dist: langchain-core (>=0.1.23,<0.2.0)
